plotlyshare/__init__.py
plotlyshare/__main__.py
plotlyshare/custom_plotly_renderer.py
plotlyshare-1.0.10.dist-info/WHEEL
plotlyshare-1.0.10.dist-info/METADATA
plotlyshare-1.0.10.dist-info/RECORD
