Metadata-Version: 2.1
Name: plotlyshare
Version: 1.0.10
Summary: Link-based sharing of `plotly` plots with a private web app
Keywords: plotly,interactive,plot
Author-email: plutonium239 <plutonium.239.811@gmail.com>
Requires-Python: >=3.7
Classifier: Programming Language :: Python :: 3
Classifier: License :: OSI Approved :: MIT License
Classifier: Operating System :: OS Independent
Requires-Dist: rich
Requires-Dist: plotly
Requires-Dist: wonderwords
Requires-Dist: requests
Project-URL: Homepage, https://github.com/plutonium-239/plotlyshare
Project-URL: Issues, https://github.com/plutonium-239/plotlyshare/issues
